README.md
requestalgorithms.py
userplay.py
randoalgo_rjm-0.1.0.dist-info/entry_points.txt
randoalgo_rjm-0.1.0.dist-info/WHEEL
randoalgo_rjm-0.1.0.dist-info/METADATA
randoalgo_rjm-0.1.0.dist-info/RECORD
