Metadata-Version: 2.1
Name: randoalgo-rjm
Version: 0.1.0
Summary: A python package that allows users get random algorithm questions
Home-page: https://github.com/startng/forward--RandoAlgo-Rjay
License: MIT
Author: Rashidat Jimoh
Requires-Python: >=3,<4
Classifier: License :: OSI Approved :: MIT License
Classifier: Programming Language :: Python :: 3
Classifier: Programming Language :: Python :: 3.4
Classifier: Programming Language :: Python :: 3.5
Classifier: Programming Language :: Python :: 3.6
Classifier: Programming Language :: Python :: 3.7
Classifier: Programming Language :: Python :: 3.8
Project-URL: Repository, https://github.com/startng/forward--RandoAlgo-Rjay
